dw_shared_kernel/__init__.py
dw_shared_kernel/application/__init__.py
dw_shared_kernel/application/exception/__init__.py
dw_shared_kernel/application/exception/base.py
dw_shared_kernel/domain/__init__.py
dw_shared_kernel/domain/entity/__init__.py
dw_shared_kernel/domain/entity/base.py
dw_shared_kernel/domain/event_bus/__init__.py
dw_shared_kernel/domain/event_bus/bus.py
dw_shared_kernel/domain/event_bus/event.py
dw_shared_kernel/domain/exception/__init__.py
dw_shared_kernel/domain/exception/base.py
dw_shared_kernel/domain/mixin/__init__.py
dw_shared_kernel/domain/mixin/change_tracker.py
dw_shared_kernel/domain/mixin/event.py
dw_shared_kernel/domain/repository/__init__.py
dw_shared_kernel/domain/repository/crud.py
dw_shared_kernel/domain/value_object/__init__.py
dw_shared_kernel/domain/value_object/base.py
dw_shared_kernel/infrastructure/__init__.py
dw_shared_kernel/infrastructure/layer.py
dw_shared_kernel/infrastructure/bus/__init__.py
dw_shared_kernel/infrastructure/bus/command/__init__.py
dw_shared_kernel/infrastructure/bus/command/bus.py
dw_shared_kernel/infrastructure/bus/command/command.py
dw_shared_kernel/infrastructure/bus/command/handler.py
dw_shared_kernel/infrastructure/bus/event/__init__.py
dw_shared_kernel/infrastructure/bus/event/bus.py
dw_shared_kernel/infrastructure/bus/event/handler.py
dw_shared_kernel/infrastructure/bus/event/repository.py
dw_shared_kernel/infrastructure/bus/middleware/__init__.py
dw_shared_kernel/infrastructure/bus/middleware/base.py
dw_shared_kernel/infrastructure/bus/mixin/__init__.py
dw_shared_kernel/infrastructure/bus/mixin/middleware.py
dw_shared_kernel/infrastructure/bus/query/__init__.py
dw_shared_kernel/infrastructure/bus/query/bus.py
dw_shared_kernel/infrastructure/bus/query/handler.py
dw_shared_kernel/infrastructure/bus/query/query.py
dw_shared_kernel/infrastructure/di/__init__.py
dw_shared_kernel/infrastructure/di/container.py
dw_shared_kernel/infrastructure/di/layer.py
dw_shared_kernel/infrastructure/di/utils.py
dw_shared_kernel-0.3.0.dist-info/METADATA
dw_shared_kernel-0.3.0.dist-info/WHEEL
dw_shared_kernel-0.3.0.dist-info/top_level.txt
dw_shared_kernel-0.3.0.dist-info/RECORD
